Metadata-Version: 2.1
Name: reshadow
Version: 0.0.21
Summary: PyShadow - ShadowCopy Anaylze Tool
Home-page: https://github.com/alicangnll/pyshadow
Author: Ali Can Gönüllü
Author-email: alicangonullu@yahoo.com
License: GNU General Public License v2.0
Project-URL: Bug Report, https://github.com/pyshadow/pymem/issues/new
Classifier: Intended Audience :: Developers
Classifier: Topic :: Software Development :: Libraries :: Python Modules
Classifier: Programming Language :: Python :: 3.8
Classifier: Programming Language :: Python :: 3.9
Classifier: Programming Language :: Python :: 3.10
Classifier: Programming Language :: Python :: 3.11
License-File: LICENSE
